{
"name": "glyph00522",
"sources": [
{
"name": "<default>",
"layerName": "<default>",
"location": {
"wght": 0
}
},
{
"name": "wght=1",
"layerName": "wght=1",
"location": {
"wght": 1.0
}
}
],
"layers": {
"<default>": {
"glyph": {
"path": {
"contours": [
{
"points": [
{
"x": 683,
"y": 773
},
{
"x": 639,
"y": 773
},
{
"x": 639,
"y": 449
},
{
"x": 647,
"y": 448
},
{
"x": 639,
"y": 447
},
{
"x": 639,
"y": -72
},
{
"x": 646,
"y": -72,
"smooth": true
},
{
"x": 668,
"y": -72,
"type": "cubic"
},
{
"x": 682,
"y": -60,
"type": "cubic"
},
{
"x": 682,
"y": -55,
"smooth": true
},
{
"x": 682,
"y": 447
},
{
"x": 674,
"y": 448
},
{
"x": 683,
"y": 449
}
],
"isClosed": true
},
{
"points": [
{
"x": 689,
"y": 316
},
{
"x": 671,
"y": 307
},
{
"x": 725,
"y": 168,
"type": "cubic"
},
{
"x": 826,
"y": 57,
"type": "cubic"
},
{
"x": 930,
"y": -5
},
{
"x": 937,
"y": 15,
"type": "cubic"
},
{
"x": 953,
"y": 27,
"type": "cubic"
},
{
"x": 973,
"y": 28
},
{
"x": 975,
"y": 38
},
{
"x": 864,
"y": 87,
"type": "cubic"
},
{
"x": 746,
"y": 195,
"type": "cubic"
}
],
"isClosed": true
},
{
"points": [
{
"x": 667,
"y": 296
},
{
"x": 667,
"y": 312
},
{
"x": 624,
"y": 312
},
{
"x": 566,
"y": 189,
"type": "cubic"
},
{
"x": 464,
"y": 79,
"type": "cubic"
},
{
"x": 335,
"y": 0
},
{
"x": 346,
"y": -18
},
{
"x": 491,
"y": 58,
"type": "cubic"
},
{
"x": 601,
"y": 164,
"type": "cubic"
}
],
"isClosed": true
},
{
"points": [
{
"x": 821,
"y": 779
},
{
"x": 831,
"y": 779
},
{
"x": 831,
"y": 406
},
{
"x": 837,
"y": 406,
"smooth": true
},
{
"x": 852,
"y": 406,
"type": "cubic"
},
{
"x": 874,
"y": 418,
"type": "cubic"
},
{
"x": 875,
"y": 424
},
{
"x": 875,
"y": 740
},
{
"x": 895,
"y": 744,
"type": "cubic"
},
{
"x": 912,
"y": 751,
"type": "cubic"
},
{
"x": 919,
"y": 759
},
{
"x": 851,
"y": 812
}
],
"isClosed": true
},
{
"points": [
{
"x": 442,
"y": 806
},
{
"x": 442,
"y": 394
},
{
"x": 448,
"y": 394,
"smooth": true
},
{
"x": 471,
"y": 394,
"type": "cubic"
},
{
"x": 486,
"y": 407,
"type": "cubic"
},
{
"x": 486,
"y": 412,
"smooth": true
},
{
"x": 486,
"y": 779
},
{
"x": 498,
"y": 779
}
],
"isClosed": true
},
{
"points": [
{
"x": 854,
"y": 464
},
{
"x": 461,
"y": 464
},
{
"x": 461,
"y": 434
},
{
"x": 854,
"y": 434
}
],
"isClosed": true
},
{
"points": [
{
"x": 854,
"y": 621
},
{
"x": 461,
"y": 621
},
{
"x": 461,
"y": 591
},
{
"x": 854,
"y": 591
}
],
"isClosed": true
},
{
"points": [
{
"x": 859,
"y": 779
},
{
"x": 461,
"y": 779
},
{
"x": 461,
"y": 749
},
{
"x": 859,
"y": 749
}
],
"isClosed": true
},
{
"points": [
{
"x": 886,
"y": 376
},
{
"x": 846,
"y": 326
},
{
"x": 364,
"y": 326
},
{
"x": 372,
"y": 296
},
{
"x": 936,
"y": 296,
"smooth": true
},
{
"x": 950,
"y": 296,
"type": "cubic"
},
{
"x": 959,
"y": 301,
"type": "cubic"
},
{
"x": 962,
"y": 312
},
{
"x": 932,
"y": 340,
"type": "cubic"
},
{
"x": 886,
"y": 376,
"type": "cubic"
}
],
"isClosed": true
},
{
"points": [
{
"x": 379,
"y": 672
},
{
"x": 294,
"y": 686
},
{
"x": 294,
"y": 386,
"type": "cubic"
},
{
"x": 242,
"y": 92,
"type": "cubic"
},
{
"x": 35,
"y": -71
},
{
"x": 49,
"y": -81
},
{
"x": 279,
"y": 77,
"type": "cubic"
},
{
"x": 332,
"y": 366,
"type": "cubic"
},
{
"x": 341,
"y": 646
},
{
"x": 362,
"y": 647,
"type": "cubic"
},
{
"x": 376,
"y": 654,
"type": "cubic"
}
],
"isClosed": true
},
{
"points": [
{
"x": 35,
"y": 568
},
{
"x": 66,
"y": 502
},
{
"x": 74,
"y": 504,
"type": "cubic"
},
{
"x": 83,
"y": 510,
"type": "cubic"
},
{
"x": 88,
"y": 523
},
{
"x": 221,
"y": 540,
"type": "cubic"
},
{
"x": 323,
"y": 562,
"type": "cubic"
},
{
"x": 402,
"y": 582
},
{
"x": 400,
"y": 599
},
{
"x": 260,
"y": 582,
"type": "cubic"
},
{
"x": 109,
"y": 569,
"type": "cubic"
}
],
"isClosed": true
},
{
"points": [
{
"x": 88,
"y": 306
},
{
"x": 72,
"y": 294
},
{
"x": 158,
"y": 234,
"type": "cubic"
},
{
"x": 284,
"y": 130,
"type": "cubic"
},
{
"x": 330,
"y": 54
},
{
"x": 392,
"y": 21,
"type": "cubic"
},
{
"x": 413,
"y": 148,
"type": "cubic"
}
],
"isClosed": true
},
{
"points": [
{
"x": 72,
"y": 294
},
{
"x": 109,
"y": 284
},
{
"x": 156,
"y": 441,
"type": "cubic"
},
{
"x": 206,
"y": 690,
"type": "cubic"
},
{
"x": 225,
"y": 816
},
{
"x": 214,
"y": 802
},
{
"x": 248,
"y": 800,
"type": "cubic"
},
{
"x": 257,
"y": 811,
"type": "cubic"
},
{
"x": 261,
"y": 824
},
{
"x": 177,
"y": 842
},
{
"x": 165,
"y": 708,
"type": "cubic"
},
{
"x": 108,
"y": 418,
"type": "cubic"
}
],
"isClosed": true
}
]
},
"xAdvance": 1000
}
},
"wght=1": {
"glyph": {
"path": {
"contours": [
{
"points": [
{
"x": 697.0,
"y": 759.0
},
{
"x": 585.0,
"y": 759.0
},
{
"x": 585.0,
"y": 440.0
},
{
"x": 599.0,
"y": 439.0
},
{
"x": 576.0,
"y": 438.0
},
{
"x": 576.0,
"y": -95.0
},
{
"x": 600.0,
"y": -95.0,
"smooth": true
},
{
"x": 666.0,
"y": -95.0,
"type": "cubic"
},
{
"x": 705.0,
"y": -68.0,
"type": "cubic"
},
{
"x": 706.0,
"y": -60.0
},
{
"x": 706.0,
"y": 438.0
},
{
"x": 683.0,
"y": 439.0
},
{
"x": 697.0,
"y": 440.0
}
],
"isClosed": true
},
{
"points": [
{
"x": 707.0,
"y": 319.0
},
{
"x": 697.0,
"y": 315.0
},
{
"x": 727.0,
"y": 160.0,
"type": "cubic"
},
{
"x": 776.0,
"y": 49.0,
"type": "cubic"
},
{
"x": 871.0,
"y": -24.0
},
{
"x": 887.0,
"y": 45.0,
"type": "cubic"
},
{
"x": 923.0,
"y": 88.0,
"type": "cubic"
},
{
"x": 972.0,
"y": 102.0
},
{
"x": 974.0,
"y": 113.0
},
{
"x": 867.0,
"y": 145.0,
"type": "cubic"
},
{
"x": 757.0,
"y": 219.0,
"type": "cubic"
}
],
"isClosed": true
},
{
"points": [
{
"x": 657.0,
"y": 303.0
},
{
"x": 657.0,
"y": 319.0
},
{
"x": 512.0,
"y": 319.0
},
{
"x": 482.0,
"y": 193.0,
"type": "cubic"
},
{
"x": 421.0,
"y": 65.0,
"type": "cubic"
},
{
"x": 327.0,
"y": -20.0
},
{
"x": 335.0,
"y": -32.0
},
{
"x": 493.0,
"y": 45.0,
"type": "cubic"
},
{
"x": 604.0,
"y": 157.0,
"type": "cubic"
}
],
"isClosed": true
},
{
"points": [
{
"x": 750.0,
"y": 772.0
},
{
"x": 760.0,
"y": 772.0
},
{
"x": 760.0,
"y": 381.0
},
{
"x": 782.0,
"y": 381.0,
"smooth": true
},
{
"x": 824.0,
"y": 381.0,
"type": "cubic"
},
{
"x": 888.0,
"y": 403.0,
"type": "cubic"
},
{
"x": 889.0,
"y": 411.0
},
{
"x": 889.0,
"y": 723.0
},
{
"x": 910.0,
"y": 727.0,
"type": "cubic"
},
{
"x": 923.0,
"y": 736.0,
"type": "cubic"
},
{
"x": 929.0,
"y": 744.0
},
{
"x": 808.0,
"y": 836.0
}
],
"isClosed": true
},
{
"points": [
{
"x": 401.0,
"y": 823.0
},
{
"x": 401.0,
"y": 368.0
},
{
"x": 424.0,
"y": 368.0,
"smooth": true
},
{
"x": 487.0,
"y": 368.0,
"type": "cubic"
},
{
"x": 524.0,
"y": 395.0,
"type": "cubic"
},
{
"x": 524.0,
"y": 403.0,
"smooth": true
},
{
"x": 524.0,
"y": 772.0
},
{
"x": 538.0,
"y": 772.0
}
],
"isClosed": true
},
{
"points": [
{
"x": 809.0,
"y": 454.0
},
{
"x": 477.0,
"y": 454.0
},
{
"x": 477.0,
"y": 426.0
},
{
"x": 809.0,
"y": 426.0
}
],
"isClosed": true
},
{
"points": [
{
"x": 814.0,
"y": 614.0
},
{
"x": 477.0,
"y": 614.0
},
{
"x": 477.0,
"y": 586.0
},
{
"x": 814.0,
"y": 586.0
}
],
"isClosed": true
},
{
"points": [
{
"x": 814.0,
"y": 772.0
},
{
"x": 477.0,
"y": 772.0
},
{
"x": 477.0,
"y": 744.0
},
{
"x": 814.0,
"y": 744.0
}
],
"isClosed": true
},
{
"points": [
{
"x": 862.0,
"y": 412.0
},
{
"x": 798.0,
"y": 319.0
},
{
"x": 347.0,
"y": 319.0
},
{
"x": 355.0,
"y": 291.0
},
{
"x": 949.0,
"y": 291.0,
"smooth": true
},
{
"x": 963.0,
"y": 291.0,
"type": "cubic"
},
{
"x": 974.0,
"y": 296.0,
"type": "cubic"
},
{
"x": 977.0,
"y": 307.0
},
{
"x": 935.0,
"y": 349.0,
"type": "cubic"
},
{
"x": 862.0,
"y": 412.0,
"type": "cubic"
}
],
"isClosed": true
},
{
"points": [
{
"x": 417.0,
"y": 676.0
},
{
"x": 255.0,
"y": 702.0
},
{
"x": 262.0,
"y": 433.0,
"type": "cubic"
},
{
"x": 225.0,
"y": 115.0,
"type": "cubic"
},
{
"x": 25.0,
"y": -86.0
},
{
"x": 36.0,
"y": -94.0
},
{
"x": 307.0,
"y": 70.0,
"type": "cubic"
},
{
"x": 363.0,
"y": 360.0,
"type": "cubic"
},
{
"x": 378.0,
"y": 649.0
},
{
"x": 402.0,
"y": 650.0,
"type": "cubic"
},
{
"x": 414.0,
"y": 660.0,
"type": "cubic"
}
],
"isClosed": true
},
{
"points": [
{
"x": 13.0,
"y": 593.0
},
{
"x": 43.0,
"y": 461.0
},
{
"x": 55.0,
"y": 462.0,
"type": "cubic"
},
{
"x": 68.0,
"y": 471.0,
"type": "cubic"
},
{
"x": 74.0,
"y": 483.0
},
{
"x": 233.0,
"y": 527.0,
"type": "cubic"
},
{
"x": 344.0,
"y": 566.0,
"type": "cubic"
},
{
"x": 429.0,
"y": 599.0
},
{
"x": 428.0,
"y": 612.0
},
{
"x": 268.0,
"y": 598.0,
"type": "cubic"
},
{
"x": 92.0,
"y": 590.0,
"type": "cubic"
}
],
"isClosed": true
},
{
"points": [
{
"x": 65.0,
"y": 306.0
},
{
"x": 44.0,
"y": 289.0
},
{
"x": 129.0,
"y": 234.0,
"type": "cubic"
},
{
"x": 232.0,
"y": 137.0,
"type": "cubic"
},
{
"x": 273.0,
"y": 51.0
},
{
"x": 374.0,
"y": -17.0,
"type": "cubic"
},
{
"x": 528.0,
"y": 180.0,
"type": "cubic"
}
],
"isClosed": true
},
{
"points": [
{
"x": 44.0,
"y": 289.0
},
{
"x": 146.0,
"y": 262.0
},
{
"x": 191.0,
"y": 427.0,
"type": "cubic"
},
{
"x": 238.0,
"y": 699.0,
"type": "cubic"
},
{
"x": 255.0,
"y": 817.0
},
{
"x": 240.0,
"y": 801.0
},
{
"x": 282.0,
"y": 802.0,
"type": "cubic"
},
{
"x": 289.0,
"y": 814.0,
"type": "cubic"
},
{
"x": 292.0,
"y": 827.0
},
{
"x": 136.0,
"y": 851.0
},
{
"x": 129.0,
"y": 732.0,
"type": "cubic"
},
{
"x": 80.0,
"y": 427.0,
"type": "cubic"
}
],
"isClosed": true
}
]
},
"xAdvance": 1000.0
}
}
}
}
