{
"name": "uni8A49",
"sources": [
{
"name": "<default>",
"layerName": "<default>",
"location": {
"wght": 0
}
},
{
"name": "wght=1",
"layerName": "wght=1",
"location": {
"wght": 1.0
}
}
],
"layers": {
"<default>": {
"glyph": {
"path": {
"contours": [
{
"points": [
{
"x": 76,
"y": 766
},
{
"x": 84,
"y": 737
},
{
"x": 318,
"y": 737,
"smooth": true
},
{
"x": 331,
"y": 737,
"type": "cubic"
},
{
"x": 341,
"y": 742,
"type": "cubic"
},
{
"x": 343,
"y": 753
},
{
"x": 316,
"y": 779,
"type": "cubic"
},
{
"x": 272,
"y": 814,
"type": "cubic"
},
{
"x": 272,
"y": 814
},
{
"x": 235,
"y": 766
}
],
"isClosed": true
},
{
"points": [
{
"x": 77,
"y": 515
},
{
"x": 85,
"y": 486
},
{
"x": 314,
"y": 486,
"smooth": true
},
{
"x": 328,
"y": 486,
"type": "cubic"
},
{
"x": 337,
"y": 491,
"type": "cubic"
},
{
"x": 340,
"y": 501
},
{
"x": 314,
"y": 526,
"type": "cubic"
},
{
"x": 275,
"y": 558,
"type": "cubic"
},
{
"x": 275,
"y": 558
},
{
"x": 240,
"y": 515
}
],
"isClosed": true
},
{
"points": [
{
"x": 77,
"y": 388
},
{
"x": 85,
"y": 359
},
{
"x": 314,
"y": 359,
"smooth": true
},
{
"x": 328,
"y": 359,
"type": "cubic"
},
{
"x": 337,
"y": 364,
"type": "cubic"
},
{
"x": 340,
"y": 374
},
{
"x": 314,
"y": 399,
"type": "cubic"
},
{
"x": 275,
"y": 431,
"type": "cubic"
},
{
"x": 275,
"y": 431
},
{
"x": 240,
"y": 388
}
],
"isClosed": true
},
{
"points": [
{
"x": 37,
"y": 641
},
{
"x": 44,
"y": 612
},
{
"x": 355,
"y": 612,
"smooth": true
},
{
"x": 368,
"y": 612,
"type": "cubic"
},
{
"x": 377,
"y": 617,
"type": "cubic"
},
{
"x": 379,
"y": 628
},
{
"x": 352,
"y": 654,
"type": "cubic"
},
{
"x": 307,
"y": 690,
"type": "cubic"
},
{
"x": 307,
"y": 690
},
{
"x": 269,
"y": 641
}
],
"isClosed": true
},
{
"points": [
{
"x": 82,
"y": 262
},
{
"x": 82,
"y": -74
},
{
"x": 89,
"y": -74,
"smooth": true
},
{
"x": 107,
"y": -74,
"type": "cubic"
},
{
"x": 126,
"y": -63,
"type": "cubic"
},
{
"x": 126,
"y": -58,
"smooth": true
},
{
"x": 126,
"y": 233
},
{
"x": 298,
"y": 233
},
{
"x": 298,
"y": 262
},
{
"x": 131,
"y": 262
},
{
"x": 82,
"y": 287
}
],
"isClosed": true
},
{
"points": [
{
"x": 269,
"y": 262
},
{
"x": 269,
"y": -45
},
{
"x": 275,
"y": -45,
"smooth": true
},
{
"x": 290,
"y": -45,
"type": "cubic"
},
{
"x": 312,
"y": -32,
"type": "cubic"
},
{
"x": 313,
"y": -27
},
{
"x": 313,
"y": 223
},
{
"x": 333,
"y": 227,
"type": "cubic"
},
{
"x": 350,
"y": 235,
"type": "cubic"
},
{
"x": 357,
"y": 242
},
{
"x": 289,
"y": 295
},
{
"x": 259,
"y": 262
}
],
"isClosed": true
},
{
"points": [
{
"x": 105,
"y": 43
},
{
"x": 105,
"y": 14
},
{
"x": 295,
"y": 14
},
{
"x": 295,
"y": 43
}
],
"isClosed": true
},
{
"points": [
{
"x": 405,
"y": 297
},
{
"x": 394,
"y": 286
},
{
"x": 467,
"y": 238,
"type": "cubic"
},
{
"x": 561,
"y": 149,
"type": "cubic"
},
{
"x": 585,
"y": 78
},
{
"x": 648,
"y": 40,
"type": "cubic"
},
{
"x": 669,
"y": 191,
"type": "cubic"
}
],
"isClosed": true
},
{
"points": [
{
"x": 479,
"y": 831
},
{
"x": 463,
"y": 678,
"type": "cubic"
},
{
"x": 398,
"y": 338,
"type": "cubic"
},
{
"x": 357,
"y": 201
},
{
"x": 376,
"y": 196,
"type": "cubic"
},
{
"x": 395,
"y": 197,
"type": "cubic"
},
{
"x": 405,
"y": 204
},
{
"x": 444,
"y": 368,
"type": "cubic"
},
{
"x": 500,
"y": 661,
"type": "cubic"
},
{
"x": 518,
"y": 793
},
{
"x": 542,
"y": 794,
"type": "cubic"
},
{
"x": 552,
"y": 803,
"type": "cubic"
},
{
"x": 556,
"y": 816
}
],
"isClosed": true
},
{
"points": [
{
"x": 695,
"y": 739
},
{
"x": 673,
"y": 730
},
{
"x": 688,
"y": 387,
"type": "cubic"
},
{
"x": 752,
"y": 99,
"type": "cubic"
},
{
"x": 912,
"y": -73
},
{
"x": 926,
"y": -52,
"type": "cubic"
},
{
"x": 948,
"y": -40,
"type": "cubic"
},
{
"x": 970,
"y": -43
},
{
"x": 974,
"y": -35
},
{
"x": 797,
"y": 118,
"type": "cubic"
},
{
"x": 714,
"y": 412,
"type": "cubic"
}
],
"isClosed": true
},
{
"points": [
{
"x": 609,
"y": 739
},
{
"x": 618,
"y": 709
},
{
"x": 922,
"y": 709
},
{
"x": 922,
"y": 739
}
],
"isClosed": true
},
{
"points": [
{
"x": 582,
"y": 593
},
{
"x": 563,
"y": 331,
"type": "cubic"
},
{
"x": 512,
"y": 77,
"type": "cubic"
},
{
"x": 340,
"y": -61
},
{
"x": 352,
"y": -75
},
{
"x": 552,
"y": 61,
"type": "cubic"
},
{
"x": 602,
"y": 311,
"type": "cubic"
},
{
"x": 627,
"y": 559
},
{
"x": 646,
"y": 561,
"type": "cubic"
},
{
"x": 656,
"y": 564,
"type": "cubic"
},
{
"x": 664,
"y": 572
},
{
"x": 603,
"y": 627
},
{
"x": 573,
"y": 593
}
],
"isClosed": true
},
{
"points": [
{
"x": 873,
"y": 739
},
{
"x": 842,
"y": 421,
"type": "cubic"
},
{
"x": 764,
"y": 111,
"type": "cubic"
},
{
"x": 536,
"y": -59
},
{
"x": 550,
"y": -72
},
{
"x": 808,
"y": 98,
"type": "cubic"
},
{
"x": 880,
"y": 402,
"type": "cubic"
},
{
"x": 916,
"y": 703
},
{
"x": 936,
"y": 705,
"type": "cubic"
},
{
"x": 946,
"y": 708,
"type": "cubic"
},
{
"x": 954,
"y": 716
},
{
"x": 894,
"y": 771
},
{
"x": 864,
"y": 739
}
],
"isClosed": true
},
{
"points": [
{
"x": 346,
"y": 593
},
{
"x": 355,
"y": 564
},
{
"x": 607,
"y": 564
},
{
"x": 607,
"y": 593
}
],
"isClosed": true
}
]
},
"xAdvance": 1000
}
},
"wght=1": {
"glyph": {
"path": {
"contours": [
{
"points": [
{
"x": 61.0,
"y": 778.0
},
{
"x": 69.0,
"y": 750.0
},
{
"x": 316.0,
"y": 750.0,
"smooth": true
},
{
"x": 330.0,
"y": 750.0,
"type": "cubic"
},
{
"x": 340.0,
"y": 755.0,
"type": "cubic"
},
{
"x": 342.0,
"y": 766.0
},
{
"x": 306.0,
"y": 801.0,
"type": "cubic"
},
{
"x": 244.0,
"y": 850.0,
"type": "cubic"
},
{
"x": 244.0,
"y": 850.0
},
{
"x": 189.0,
"y": 778.0
}
],
"isClosed": true
},
{
"points": [
{
"x": 56.0,
"y": 520.0
},
{
"x": 64.0,
"y": 492.0
},
{
"x": 318.0,
"y": 492.0,
"smooth": true
},
{
"x": 332.0,
"y": 492.0,
"type": "cubic"
},
{
"x": 342.0,
"y": 497.0,
"type": "cubic"
},
{
"x": 345.0,
"y": 508.0
},
{
"x": 309.0,
"y": 541.0,
"type": "cubic"
},
{
"x": 250.0,
"y": 589.0,
"type": "cubic"
},
{
"x": 250.0,
"y": 589.0
},
{
"x": 198.0,
"y": 520.0
}
],
"isClosed": true
},
{
"points": [
{
"x": 56.0,
"y": 389.0
},
{
"x": 64.0,
"y": 361.0
},
{
"x": 318.0,
"y": 361.0,
"smooth": true
},
{
"x": 332.0,
"y": 361.0,
"type": "cubic"
},
{
"x": 342.0,
"y": 366.0,
"type": "cubic"
},
{
"x": 345.0,
"y": 377.0
},
{
"x": 309.0,
"y": 410.0,
"type": "cubic"
},
{
"x": 250.0,
"y": 458.0,
"type": "cubic"
},
{
"x": 250.0,
"y": 458.0
},
{
"x": 198.0,
"y": 389.0
}
],
"isClosed": true
},
{
"points": [
{
"x": 20.0,
"y": 651.0
},
{
"x": 28.0,
"y": 623.0
},
{
"x": 351.0,
"y": 623.0,
"smooth": true
},
{
"x": 365.0,
"y": 623.0,
"type": "cubic"
},
{
"x": 375.0,
"y": 628.0,
"type": "cubic"
},
{
"x": 377.0,
"y": 639.0
},
{
"x": 340.0,
"y": 674.0,
"type": "cubic"
},
{
"x": 278.0,
"y": 724.0,
"type": "cubic"
},
{
"x": 278.0,
"y": 724.0
},
{
"x": 223.0,
"y": 651.0
}
],
"isClosed": true
},
{
"points": [
{
"x": 55.0,
"y": 250.0
},
{
"x": 55.0,
"y": -95.0
},
{
"x": 72.0,
"y": -95.0,
"smooth": true
},
{
"x": 123.0,
"y": -95.0,
"type": "cubic"
},
{
"x": 175.0,
"y": -68.0,
"type": "cubic"
},
{
"x": 175.0,
"y": -57.0,
"smooth": true
},
{
"x": 175.0,
"y": 222.0
},
{
"x": 270.0,
"y": 222.0
},
{
"x": 270.0,
"y": 250.0
},
{
"x": 178.0,
"y": 250.0
},
{
"x": 55.0,
"y": 299.0
}
],
"isClosed": true
},
{
"points": [
{
"x": 217.0,
"y": 250.0
},
{
"x": 217.0,
"y": -45.0
},
{
"x": 238.0,
"y": -45.0,
"smooth": true
},
{
"x": 279.0,
"y": -45.0,
"type": "cubic"
},
{
"x": 337.0,
"y": -19.0,
"type": "cubic"
},
{
"x": 338.0,
"y": -10.0
},
{
"x": 338.0,
"y": 208.0
},
{
"x": 354.0,
"y": 211.0,
"type": "cubic"
},
{
"x": 364.0,
"y": 218.0,
"type": "cubic"
},
{
"x": 369.0,
"y": 225.0
},
{
"x": 261.0,
"y": 305.0
},
{
"x": 208.0,
"y": 250.0
}
],
"isClosed": true
},
{
"points": [
{
"x": 124.0,
"y": 34.0
},
{
"x": 124.0,
"y": 6.0
},
{
"x": 275.0,
"y": 6.0
},
{
"x": 275.0,
"y": 34.0
}
],
"isClosed": true
},
{
"points": [
{
"x": 407.0,
"y": 330.0
},
{
"x": 397.0,
"y": 324.0
},
{
"x": 454.0,
"y": 251.0,
"type": "cubic"
},
{
"x": 522.0,
"y": 144.0,
"type": "cubic"
},
{
"x": 547.0,
"y": 55.0
},
{
"x": 664.0,
"y": -27.0,
"type": "cubic"
},
{
"x": 746.0,
"y": 212.0,
"type": "cubic"
}
],
"isClosed": true
},
{
"points": [
{
"x": 418.0,
"y": 853.0
},
{
"x": 413.0,
"y": 713.0,
"type": "cubic"
},
{
"x": 366.0,
"y": 364.0,
"type": "cubic"
},
{
"x": 330.0,
"y": 205.0
},
{
"x": 380.0,
"y": 193.0,
"type": "cubic"
},
{
"x": 426.0,
"y": 198.0,
"type": "cubic"
},
{
"x": 447.0,
"y": 214.0
},
{
"x": 478.0,
"y": 375.0,
"type": "cubic"
},
{
"x": 518.0,
"y": 685.0,
"type": "cubic"
},
{
"x": 529.0,
"y": 811.0
},
{
"x": 556.0,
"y": 814.0,
"type": "cubic"
},
{
"x": 564.0,
"y": 825.0,
"type": "cubic"
},
{
"x": 566.0,
"y": 838.0
}
],
"isClosed": true
},
{
"points": [
{
"x": 697.0,
"y": 756.0
},
{
"x": 679.0,
"y": 751.0
},
{
"x": 686.0,
"y": 309.0,
"type": "cubic"
},
{
"x": 718.0,
"y": 90.0,
"type": "cubic"
},
{
"x": 852.0,
"y": -97.0
},
{
"x": 882.0,
"y": -42.0,
"type": "cubic"
},
{
"x": 933.0,
"y": -11.0,
"type": "cubic"
},
{
"x": 988.0,
"y": -10.0
},
{
"x": 992.0,
"y": 0.0
},
{
"x": 818.0,
"y": 147.0,
"type": "cubic"
},
{
"x": 714.0,
"y": 359.0,
"type": "cubic"
}
],
"isClosed": true
},
{
"points": [
{
"x": 605.0,
"y": 757.0
},
{
"x": 614.0,
"y": 729.0
},
{
"x": 875.0,
"y": 729.0
},
{
"x": 875.0,
"y": 757.0
}
],
"isClosed": true
},
{
"points": [
{
"x": 542.0,
"y": 597.0
},
{
"x": 527.0,
"y": 309.0,
"type": "cubic"
},
{
"x": 470.0,
"y": 55.0,
"type": "cubic"
},
{
"x": 267.0,
"y": -81.0
},
{
"x": 275.0,
"y": -92.0
},
{
"x": 567.0,
"y": 21.0,
"type": "cubic"
},
{
"x": 632.0,
"y": 275.0,
"type": "cubic"
},
{
"x": 657.0,
"y": 549.0
},
{
"x": 680.0,
"y": 552.0,
"type": "cubic"
},
{
"x": 690.0,
"y": 556.0,
"type": "cubic"
},
{
"x": 696.0,
"y": 567.0
},
{
"x": 589.0,
"y": 660.0
},
{
"x": 530.0,
"y": 597.0
}
],
"isClosed": true
},
{
"points": [
{
"x": 813.0,
"y": 757.0
},
{
"x": 793.0,
"y": 418.0,
"type": "cubic"
},
{
"x": 721.0,
"y": 96.0,
"type": "cubic"
},
{
"x": 495.0,
"y": -89.0
},
{
"x": 504.0,
"y": -99.0
},
{
"x": 835.0,
"y": 58.0,
"type": "cubic"
},
{
"x": 908.0,
"y": 381.0,
"type": "cubic"
},
{
"x": 940.0,
"y": 703.0
},
{
"x": 964.0,
"y": 707.0,
"type": "cubic"
},
{
"x": 974.0,
"y": 711.0,
"type": "cubic"
},
{
"x": 981.0,
"y": 723.0
},
{
"x": 865.0,
"y": 827.0
},
{
"x": 800.0,
"y": 757.0
}
],
"isClosed": true
},
{
"points": [
{
"x": 322.0,
"y": 597.0
},
{
"x": 331.0,
"y": 569.0
},
{
"x": 601.0,
"y": 569.0
},
{
"x": 601.0,
"y": 597.0
}
],
"isClosed": true
}
]
},
"xAdvance": 1000.0
}
}
}
}
