{
"name": "uni8A5B",
"sources": [
{
"name": "<default>",
"layerName": "<default>",
"location": {
"wght": 0
}
},
{
"name": "wght=1",
"layerName": "wght=1",
"location": {
"wght": 1.0
}
}
],
"layers": {
"<default>": {
"glyph": {
"path": {
"contours": [
{
"points": [
{
"x": 376,
"y": -2
},
{
"x": 384,
"y": -31
},
{
"x": 952,
"y": -31,
"smooth": true
},
{
"x": 964,
"y": -31,
"type": "cubic"
},
{
"x": 974,
"y": -27,
"type": "cubic"
},
{
"x": 976,
"y": -16
},
{
"x": 951,
"y": 14,
"type": "cubic"
},
{
"x": 906,
"y": 54,
"type": "cubic"
},
{
"x": 906,
"y": 54
},
{
"x": 867,
"y": -2
}
],
"isClosed": true
},
{
"points": [
{
"x": 515,
"y": 520
},
{
"x": 515,
"y": 491
},
{
"x": 828,
"y": 491
},
{
"x": 828,
"y": 520
}
],
"isClosed": true
},
{
"points": [
{
"x": 515,
"y": 260
},
{
"x": 515,
"y": 231
},
{
"x": 828,
"y": 231
},
{
"x": 828,
"y": 260
}
],
"isClosed": true
},
{
"points": [
{
"x": 497,
"y": 781
},
{
"x": 497,
"y": -10
},
{
"x": 542,
"y": -10
},
{
"x": 542,
"y": 752
},
{
"x": 813,
"y": 752
},
{
"x": 813,
"y": -10
},
{
"x": 858,
"y": -10
},
{
"x": 858,
"y": 742
},
{
"x": 882,
"y": 745,
"type": "cubic"
},
{
"x": 896,
"y": 750,
"type": "cubic"
},
{
"x": 903,
"y": 759
},
{
"x": 829,
"y": 819
},
{
"x": 801,
"y": 781
},
{
"x": 554,
"y": 781
},
{
"x": 497,
"y": 808
}
],
"isClosed": true
},
{
"points": [
{
"x": 82,
"y": 775
},
{
"x": 90,
"y": 746
},
{
"x": 362,
"y": 746,
"smooth": true
},
{
"x": 375,
"y": 746,
"type": "cubic"
},
{
"x": 384,
"y": 751,
"type": "cubic"
},
{
"x": 387,
"y": 761
},
{
"x": 360,
"y": 788,
"type": "cubic"
},
{
"x": 315,
"y": 823,
"type": "cubic"
},
{
"x": 315,
"y": 823
},
{
"x": 278,
"y": 775
}
],
"isClosed": true
},
{
"points": [
{
"x": 87,
"y": 524
},
{
"x": 95,
"y": 495
},
{
"x": 362,
"y": 495,
"smooth": true
},
{
"x": 374,
"y": 495,
"type": "cubic"
},
{
"x": 383,
"y": 499,
"type": "cubic"
},
{
"x": 386,
"y": 510
},
{
"x": 362,
"y": 535,
"type": "cubic"
},
{
"x": 321,
"y": 566,
"type": "cubic"
},
{
"x": 321,
"y": 566
},
{
"x": 287,
"y": 524
}
],
"isClosed": true
},
{
"points": [
{
"x": 87,
"y": 397
},
{
"x": 95,
"y": 367
},
{
"x": 362,
"y": 367,
"smooth": true
},
{
"x": 374,
"y": 367,
"type": "cubic"
},
{
"x": 383,
"y": 372,
"type": "cubic"
},
{
"x": 386,
"y": 383
},
{
"x": 362,
"y": 408,
"type": "cubic"
},
{
"x": 321,
"y": 439,
"type": "cubic"
},
{
"x": 321,
"y": 439
},
{
"x": 287,
"y": 397
}
],
"isClosed": true
},
{
"points": [
{
"x": 43,
"y": 650
},
{
"x": 51,
"y": 621
},
{
"x": 423,
"y": 621,
"smooth": true
},
{
"x": 435,
"y": 621,
"type": "cubic"
},
{
"x": 445,
"y": 626,
"type": "cubic"
},
{
"x": 447,
"y": 636
},
{
"x": 420,
"y": 663,
"type": "cubic"
},
{
"x": 374,
"y": 698,
"type": "cubic"
},
{
"x": 374,
"y": 698
},
{
"x": 336,
"y": 650
}
],
"isClosed": true
},
{
"points": [
{
"x": 93,
"y": 271
},
{
"x": 93,
"y": -77
},
{
"x": 101,
"y": -77,
"smooth": true
},
{
"x": 118,
"y": -77,
"type": "cubic"
},
{
"x": 137,
"y": -66,
"type": "cubic"
},
{
"x": 137,
"y": -61,
"smooth": true
},
{
"x": 137,
"y": 241
},
{
"x": 339,
"y": 241
},
{
"x": 339,
"y": 271
},
{
"x": 142,
"y": 271
},
{
"x": 93,
"y": 296
}
],
"isClosed": true
},
{
"points": [
{
"x": 311,
"y": 271
},
{
"x": 311,
"y": -57
},
{
"x": 317,
"y": -57,
"smooth": true
},
{
"x": 332,
"y": -57,
"type": "cubic"
},
{
"x": 355,
"y": -44,
"type": "cubic"
},
{
"x": 356,
"y": -38
},
{
"x": 356,
"y": 232
},
{
"x": 375,
"y": 236,
"type": "cubic"
},
{
"x": 392,
"y": 243,
"type": "cubic"
},
{
"x": 399,
"y": 251
},
{
"x": 331,
"y": 303
},
{
"x": 302,
"y": 271
}
],
"isClosed": true
},
{
"points": [
{
"x": 116,
"y": 37
},
{
"x": 116,
"y": 7
},
{
"x": 330,
"y": 7
},
{
"x": 330,
"y": 37
}
],
"isClosed": true
}
]
},
"xAdvance": 1000
}
},
"wght=1": {
"glyph": {
"path": {
"contours": [
{
"points": [
{
"x": 387.0,
"y": -31.0
},
{
"x": 395.0,
"y": -59.0
},
{
"x": 973.0,
"y": -59.0,
"smooth": true
},
{
"x": 986.0,
"y": -59.0,
"type": "cubic"
},
{
"x": 996.0,
"y": -54.0,
"type": "cubic"
},
{
"x": 999.0,
"y": -43.0
},
{
"x": 972.0,
"y": -4.0,
"type": "cubic"
},
{
"x": 915.0,
"y": 60.0,
"type": "cubic"
},
{
"x": 915.0,
"y": 60.0
},
{
"x": 866.0,
"y": -31.0
}
],
"isClosed": true
},
{
"points": [
{
"x": 539.0,
"y": 514.0
},
{
"x": 539.0,
"y": 486.0
},
{
"x": 809.0,
"y": 486.0
},
{
"x": 809.0,
"y": 514.0
}
],
"isClosed": true
},
{
"points": [
{
"x": 539.0,
"y": 245.0
},
{
"x": 539.0,
"y": 217.0
},
{
"x": 809.0,
"y": 217.0
},
{
"x": 809.0,
"y": 245.0
}
],
"isClosed": true
},
{
"points": [
{
"x": 457.0,
"y": 773.0
},
{
"x": 457.0,
"y": -43.0
},
{
"x": 589.0,
"y": -43.0
},
{
"x": 589.0,
"y": 745.0
},
{
"x": 739.0,
"y": 745.0
},
{
"x": 739.0,
"y": -43.0
},
{
"x": 877.0,
"y": -43.0
},
{
"x": 877.0,
"y": 731.0
},
{
"x": 903.0,
"y": 735.0,
"type": "cubic"
},
{
"x": 916.0,
"y": 741.0,
"type": "cubic"
},
{
"x": 923.0,
"y": 752.0
},
{
"x": 786.0,
"y": 847.0
},
{
"x": 730.0,
"y": 773.0
},
{
"x": 597.0,
"y": 773.0
},
{
"x": 457.0,
"y": 826.0
}
],
"isClosed": true
},
{
"points": [
{
"x": 63.0,
"y": 778.0
},
{
"x": 71.0,
"y": 750.0
},
{
"x": 362.0,
"y": 750.0,
"smooth": true
},
{
"x": 376.0,
"y": 750.0,
"type": "cubic"
},
{
"x": 386.0,
"y": 755.0,
"type": "cubic"
},
{
"x": 389.0,
"y": 766.0
},
{
"x": 350.0,
"y": 802.0,
"type": "cubic"
},
{
"x": 286.0,
"y": 854.0,
"type": "cubic"
},
{
"x": 286.0,
"y": 854.0
},
{
"x": 229.0,
"y": 778.0
}
],
"isClosed": true
},
{
"points": [
{
"x": 63.0,
"y": 520.0
},
{
"x": 71.0,
"y": 492.0
},
{
"x": 367.0,
"y": 492.0,
"smooth": true
},
{
"x": 381.0,
"y": 492.0,
"type": "cubic"
},
{
"x": 391.0,
"y": 497.0,
"type": "cubic"
},
{
"x": 394.0,
"y": 508.0
},
{
"x": 356.0,
"y": 543.0,
"type": "cubic"
},
{
"x": 294.0,
"y": 594.0,
"type": "cubic"
},
{
"x": 294.0,
"y": 594.0
},
{
"x": 238.0,
"y": 520.0
}
],
"isClosed": true
},
{
"points": [
{
"x": 63.0,
"y": 389.0
},
{
"x": 71.0,
"y": 361.0
},
{
"x": 367.0,
"y": 361.0,
"smooth": true
},
{
"x": 381.0,
"y": 361.0,
"type": "cubic"
},
{
"x": 391.0,
"y": 366.0,
"type": "cubic"
},
{
"x": 394.0,
"y": 377.0
},
{
"x": 356.0,
"y": 412.0,
"type": "cubic"
},
{
"x": 294.0,
"y": 463.0,
"type": "cubic"
},
{
"x": 294.0,
"y": 463.0
},
{
"x": 238.0,
"y": 389.0
}
],
"isClosed": true
},
{
"points": [
{
"x": 18.0,
"y": 651.0
},
{
"x": 26.0,
"y": 623.0
},
{
"x": 419.0,
"y": 623.0,
"smooth": true
},
{
"x": 433.0,
"y": 623.0,
"type": "cubic"
},
{
"x": 443.0,
"y": 628.0,
"type": "cubic"
},
{
"x": 446.0,
"y": 639.0
},
{
"x": 407.0,
"y": 675.0,
"type": "cubic"
},
{
"x": 343.0,
"y": 726.0,
"type": "cubic"
},
{
"x": 343.0,
"y": 726.0
},
{
"x": 287.0,
"y": 651.0
}
],
"isClosed": true
},
{
"points": [
{
"x": 62.0,
"y": 250.0
},
{
"x": 62.0,
"y": -95.0
},
{
"x": 80.0,
"y": -95.0,
"smooth": true
},
{
"x": 133.0,
"y": -95.0,
"type": "cubic"
},
{
"x": 187.0,
"y": -67.0,
"type": "cubic"
},
{
"x": 187.0,
"y": -56.0,
"smooth": true
},
{
"x": 187.0,
"y": 222.0
},
{
"x": 324.0,
"y": 222.0
},
{
"x": 324.0,
"y": 250.0
},
{
"x": 191.0,
"y": 250.0
},
{
"x": 62.0,
"y": 301.0
}
],
"isClosed": true
},
{
"points": [
{
"x": 252.0,
"y": 250.0
},
{
"x": 252.0,
"y": -78.0
},
{
"x": 274.0,
"y": -78.0,
"smooth": true
},
{
"x": 317.0,
"y": -78.0,
"type": "cubic"
},
{
"x": 378.0,
"y": -52.0,
"type": "cubic"
},
{
"x": 378.0,
"y": -43.0,
"smooth": true
},
{
"x": 378.0,
"y": 205.0
},
{
"x": 397.0,
"y": 208.0,
"type": "cubic"
},
{
"x": 408.0,
"y": 216.0,
"type": "cubic"
},
{
"x": 414.0,
"y": 223.0
},
{
"x": 299.0,
"y": 310.0
},
{
"x": 243.0,
"y": 250.0
}
],
"isClosed": true
},
{
"points": [
{
"x": 126.0,
"y": 34.0
},
{
"x": 126.0,
"y": 6.0
},
{
"x": 324.0,
"y": 6.0
},
{
"x": 324.0,
"y": 34.0
}
],
"isClosed": true
}
]
},
"xAdvance": 1000.0
}
}
}
}
