{
"name": "glyph00963",
"sources": [
{
"name": "<default>",
"layerName": "<default>",
"location": {
"wght": 0
}
},
{
"name": "wght=1",
"layerName": "wght=1",
"location": {
"wght": 1.0
}
}
],
"layers": {
"<default>": {
"glyph": {
"path": {
"contours": [
{
"points": [
{
"x": 376,
"y": 837
},
{
"x": 363,
"y": 830
},
{
"x": 393,
"y": 797,
"type": "cubic"
},
{
"x": 422,
"y": 739,
"type": "cubic"
},
{
"x": 424,
"y": 694
},
{
"x": 473,
"y": 652,
"type": "cubic"
},
{
"x": 523,
"y": 761,
"type": "cubic"
}
],
"isClosed": true
},
{
"points": [
{
"x": 667,
"y": -53,
"smooth": true
},
{
"x": 667,
"y": 349
},
{
"x": 679,
"y": 349
},
{
"x": 623,
"y": 375
},
{
"x": 623,
"y": -71
},
{
"x": 630,
"y": -71,
"smooth": true
},
{
"x": 651,
"y": -71,
"type": "cubic"
},
{
"x": 667,
"y": -58,
"type": "cubic"
}
],
"isClosed": true
},
{
"points": [
{
"x": 968,
"y": 736
},
{
"x": 887,
"y": 766
},
{
"x": 826,
"y": 591,
"type": "cubic"
},
{
"x": 698,
"y": 364,
"type": "cubic"
},
{
"x": 539,
"y": 217
},
{
"x": 552,
"y": 205
},
{
"x": 728,
"y": 346,
"type": "cubic"
},
{
"x": 859,
"y": 562,
"type": "cubic"
},
{
"x": 927,
"y": 723
},
{
"x": 953,
"y": 720,
"type": "cubic"
},
{
"x": 962,
"y": 725,
"type": "cubic"
}
],
"isClosed": true
},
{
"points": [
{
"x": 764,
"y": 826
},
{
"x": 687,
"y": 835
},
{
"x": 687,
"y": 470
},
{
"x": 731,
"y": 470
},
{
"x": 731,
"y": 801
},
{
"x": 753,
"y": 804,
"type": "cubic"
},
{
"x": 762,
"y": 812,
"type": "cubic"
}
],
"isClosed": true
},
{
"points": [
{
"x": 893,
"y": 529
},
{
"x": 857,
"y": 485
},
{
"x": 546,
"y": 485
},
{
"x": 554,
"y": 455
},
{
"x": 934,
"y": 455,
"smooth": true
},
{
"x": 948,
"y": 455,
"type": "cubic"
},
{
"x": 957,
"y": 460,
"type": "cubic"
},
{
"x": 960,
"y": 471
},
{
"x": 934,
"y": 497,
"type": "cubic"
},
{
"x": 893,
"y": 529,
"type": "cubic"
}
],
"isClosed": true
},
{
"points": [
{
"x": 807,
"y": 720
},
{
"x": 775,
"y": 681
},
{
"x": 598,
"y": 681
},
{
"x": 606,
"y": 651
},
{
"x": 842,
"y": 651,
"smooth": true
},
{
"x": 855,
"y": 651,
"type": "cubic"
},
{
"x": 864,
"y": 656,
"type": "cubic"
},
{
"x": 867,
"y": 667
},
{
"x": 843,
"y": 691,
"type": "cubic"
},
{
"x": 807,
"y": 720,
"type": "cubic"
}
],
"isClosed": true
},
{
"points": [
{
"x": 831,
"y": 349
},
{
"x": 841,
"y": 349
},
{
"x": 841,
"y": -57
},
{
"x": 847,
"y": -57,
"smooth": true
},
{
"x": 863,
"y": -57,
"type": "cubic"
},
{
"x": 884,
"y": -45,
"type": "cubic"
},
{
"x": 885,
"y": -38
},
{
"x": 885,
"y": 310
},
{
"x": 905,
"y": 314,
"type": "cubic"
},
{
"x": 923,
"y": 321,
"type": "cubic"
},
{
"x": 930,
"y": 329
},
{
"x": 861,
"y": 382
}
],
"isClosed": true
},
{
"points": [
{
"x": 861,
"y": 30
},
{
"x": 656,
"y": 30
},
{
"x": 656,
"y": 0
},
{
"x": 861,
"y": 0
}
],
"isClosed": true
},
{
"points": [
{
"x": 856,
"y": 190
},
{
"x": 656,
"y": 190
},
{
"x": 656,
"y": 160
},
{
"x": 856,
"y": 160
}
],
"isClosed": true
},
{
"points": [
{
"x": 861,
"y": 349
},
{
"x": 656,
"y": 349
},
{
"x": 656,
"y": 319
},
{
"x": 861,
"y": 319
}
],
"isClosed": true
},
{
"points": [
{
"x": 484,
"y": 272
},
{
"x": 494,
"y": 272
},
{
"x": 494,
"y": -60
},
{
"x": 500,
"y": -60,
"smooth": true
},
{
"x": 516,
"y": -60,
"type": "cubic"
},
{
"x": 537,
"y": -47,
"type": "cubic"
},
{
"x": 538,
"y": -41
},
{
"x": 538,
"y": 233
},
{
"x": 558,
"y": 237,
"type": "cubic"
},
{
"x": 576,
"y": 244,
"type": "cubic"
},
{
"x": 582,
"y": 252
},
{
"x": 514,
"y": 305
}
],
"isClosed": true
},
{
"points": [
{
"x": 327,
"y": 298
},
{
"x": 327,
"y": -71
},
{
"x": 333,
"y": -71,
"smooth": true
},
{
"x": 355,
"y": -71,
"type": "cubic"
},
{
"x": 370,
"y": -58,
"type": "cubic"
},
{
"x": 370,
"y": -54,
"smooth": true
},
{
"x": 370,
"y": 272
},
{
"x": 382,
"y": 272
}
],
"isClosed": true
},
{
"points": [
{
"x": 509,
"y": 432
},
{
"x": 480,
"y": 395
},
{
"x": 330,
"y": 395
},
{
"x": 338,
"y": 365
},
{
"x": 542,
"y": 365,
"smooth": true
},
{
"x": 555,
"y": 365,
"type": "cubic"
},
{
"x": 563,
"y": 370,
"type": "cubic"
},
{
"x": 566,
"y": 381
},
{
"x": 544,
"y": 404,
"type": "cubic"
},
{
"x": 509,
"y": 432,
"type": "cubic"
}
],
"isClosed": true
},
{
"points": [
{
"x": 508,
"y": 561
},
{
"x": 479,
"y": 524
},
{
"x": 329,
"y": 524
},
{
"x": 337,
"y": 494
},
{
"x": 541,
"y": 494,
"smooth": true
},
{
"x": 554,
"y": 494,
"type": "cubic"
},
{
"x": 562,
"y": 499,
"type": "cubic"
},
{
"x": 565,
"y": 510
},
{
"x": 543,
"y": 533,
"type": "cubic"
},
{
"x": 508,
"y": 561,
"type": "cubic"
}
],
"isClosed": true
},
{
"points": [
{
"x": 542,
"y": 705
},
{
"x": 509,
"y": 665
},
{
"x": 309,
"y": 665
},
{
"x": 317,
"y": 635
},
{
"x": 579,
"y": 635,
"smooth": true
},
{
"x": 593,
"y": 635,
"type": "cubic"
},
{
"x": 602,
"y": 640,
"type": "cubic"
},
{
"x": 604,
"y": 651
},
{
"x": 580,
"y": 675,
"type": "cubic"
},
{
"x": 542,
"y": 705,
"type": "cubic"
}
],
"isClosed": true
},
{
"points": [
{
"x": 517,
"y": 39
},
{
"x": 359,
"y": 39
},
{
"x": 359,
"y": 9
},
{
"x": 517,
"y": 9
}
],
"isClosed": true
},
{
"points": [
{
"x": 512,
"y": 272
},
{
"x": 354,
"y": 272
},
{
"x": 354,
"y": 242
},
{
"x": 512,
"y": 242
}
],
"isClosed": true
},
{
"points": [
{
"x": 212,
"y": 488
},
{
"x": 200,
"y": 481
},
{
"x": 228,
"y": 450,
"type": "cubic"
},
{
"x": 264,
"y": 397,
"type": "cubic"
},
{
"x": 277,
"y": 360
},
{
"x": 325,
"y": 326,
"type": "cubic"
},
{
"x": 365,
"y": 421,
"type": "cubic"
}
],
"isClosed": true
},
{
"points": [
{
"x": 258,
"y": 828
},
{
"x": 179,
"y": 837
},
{
"x": 179,
"y": -72
},
{
"x": 189,
"y": -72,
"smooth": true
},
{
"x": 204,
"y": -72,
"type": "cubic"
},
{
"x": 223,
"y": -60,
"type": "cubic"
},
{
"x": 223,
"y": -52,
"smooth": true
},
{
"x": 223,
"y": 800
},
{
"x": 248,
"y": 804,
"type": "cubic"
},
{
"x": 256,
"y": 813,
"type": "cubic"
}
],
"isClosed": true
},
{
"points": [
{
"x": 213,
"y": 587
},
{
"x": 213,
"y": 603
},
{
"x": 168,
"y": 603
},
{
"x": 145,
"y": 448,
"type": "cubic"
},
{
"x": 102,
"y": 295,
"type": "cubic"
},
{
"x": 27,
"y": 172
},
{
"x": 43,
"y": 159
},
{
"x": 134,
"y": 280,
"type": "cubic"
},
{
"x": 186,
"y": 427,
"type": "cubic"
}
],
"isClosed": true
},
{
"points": [
{
"x": 279,
"y": 651
},
{
"x": 239,
"y": 603
},
{
"x": 48,
"y": 603
},
{
"x": 56,
"y": 573
},
{
"x": 326,
"y": 573,
"smooth": true
},
{
"x": 339,
"y": 573,
"type": "cubic"
},
{
"x": 348,
"y": 578,
"type": "cubic"
},
{
"x": 350,
"y": 589
},
{
"x": 323,
"y": 616,
"type": "cubic"
},
{
"x": 279,
"y": 651,
"type": "cubic"
}
],
"isClosed": true
}
]
},
"xAdvance": 1000
}
},
"wght=1": {
"glyph": {
"path": {
"contours": [
{
"points": [
{
"x": 364.0,
"y": 839.0
},
{
"x": 355.0,
"y": 834.0
},
{
"x": 374.0,
"y": 799.0,
"type": "cubic"
},
{
"x": 394.0,
"y": 746.0,
"type": "cubic"
},
{
"x": 397.0,
"y": 699.0
},
{
"x": 486.0,
"y": 622.0,
"type": "cubic"
},
{
"x": 598.0,
"y": 791.0,
"type": "cubic"
}
],
"isClosed": true
},
{
"points": [
{
"x": 721.0,
"y": -50.0,
"smooth": true
},
{
"x": 721.0,
"y": 366.0
},
{
"x": 734.0,
"y": 366.0
},
{
"x": 609.0,
"y": 413.0
},
{
"x": 609.0,
"y": -83.0
},
{
"x": 629.0,
"y": -83.0,
"smooth": true
},
{
"x": 686.0,
"y": -83.0,
"type": "cubic"
},
{
"x": 721.0,
"y": -58.0,
"type": "cubic"
}
],
"isClosed": true
},
{
"points": [
{
"x": 982.0,
"y": 739.0
},
{
"x": 846.0,
"y": 790.0
},
{
"x": 803.0,
"y": 627.0,
"type": "cubic"
},
{
"x": 702.0,
"y": 417.0,
"type": "cubic"
},
{
"x": 552.0,
"y": 285.0
},
{
"x": 562.0,
"y": 274.0
},
{
"x": 754.0,
"y": 383.0,
"type": "cubic"
},
{
"x": 877.0,
"y": 569.0,
"type": "cubic"
},
{
"x": 943.0,
"y": 722.0
},
{
"x": 968.0,
"y": 721.0,
"type": "cubic"
},
{
"x": 978.0,
"y": 728.0,
"type": "cubic"
}
],
"isClosed": true
},
{
"points": [
{
"x": 792.0,
"y": 843.0
},
{
"x": 662.0,
"y": 855.0
},
{
"x": 662.0,
"y": 475.0
},
{
"x": 763.0,
"y": 475.0
},
{
"x": 763.0,
"y": 820.0
},
{
"x": 784.0,
"y": 823.0,
"type": "cubic"
},
{
"x": 790.0,
"y": 831.0,
"type": "cubic"
}
],
"isClosed": true
},
{
"points": [
{
"x": 885.0,
"y": 558.0
},
{
"x": 835.0,
"y": 484.0
},
{
"x": 562.0,
"y": 484.0
},
{
"x": 570.0,
"y": 456.0
},
{
"x": 947.0,
"y": 456.0,
"smooth": true
},
{
"x": 961.0,
"y": 456.0,
"type": "cubic"
},
{
"x": 971.0,
"y": 461.0,
"type": "cubic"
},
{
"x": 973.0,
"y": 472.0
},
{
"x": 942.0,
"y": 507.0,
"type": "cubic"
},
{
"x": 885.0,
"y": 558.0,
"type": "cubic"
}
],
"isClosed": true
},
{
"points": [
{
"x": 789.0,
"y": 748.0
},
{
"x": 748.0,
"y": 688.0
},
{
"x": 592.0,
"y": 688.0
},
{
"x": 600.0,
"y": 660.0
},
{
"x": 837.0,
"y": 660.0,
"smooth": true
},
{
"x": 850.0,
"y": 660.0,
"type": "cubic"
},
{
"x": 860.0,
"y": 665.0,
"type": "cubic"
},
{
"x": 862.0,
"y": 676.0
},
{
"x": 836.0,
"y": 706.0,
"type": "cubic"
},
{
"x": 789.0,
"y": 748.0,
"type": "cubic"
}
],
"isClosed": true
},
{
"points": [
{
"x": 766.0,
"y": 366.0
},
{
"x": 776.0,
"y": 366.0
},
{
"x": 776.0,
"y": -63.0
},
{
"x": 796.0,
"y": -63.0,
"smooth": true
},
{
"x": 837.0,
"y": -63.0,
"type": "cubic"
},
{
"x": 896.0,
"y": -40.0,
"type": "cubic"
},
{
"x": 897.0,
"y": -33.0
},
{
"x": 897.0,
"y": 321.0
},
{
"x": 915.0,
"y": 325.0,
"type": "cubic"
},
{
"x": 927.0,
"y": 333.0,
"type": "cubic"
},
{
"x": 933.0,
"y": 340.0
},
{
"x": 821.0,
"y": 425.0
}
],
"isClosed": true
},
{
"points": [
{
"x": 848.0,
"y": 18.0
},
{
"x": 664.0,
"y": 18.0
},
{
"x": 664.0,
"y": -10.0
},
{
"x": 848.0,
"y": -10.0
}
],
"isClosed": true
},
{
"points": [
{
"x": 848.0,
"y": 197.0
},
{
"x": 664.0,
"y": 197.0
},
{
"x": 664.0,
"y": 169.0
},
{
"x": 848.0,
"y": 169.0
}
],
"isClosed": true
},
{
"points": [
{
"x": 848.0,
"y": 366.0
},
{
"x": 664.0,
"y": 366.0
},
{
"x": 664.0,
"y": 338.0
},
{
"x": 848.0,
"y": 338.0
}
],
"isClosed": true
},
{
"points": [
{
"x": 460.0,
"y": 284.0
},
{
"x": 468.0,
"y": 284.0
},
{
"x": 468.0,
"y": -53.0
},
{
"x": 486.0,
"y": -53.0,
"smooth": true
},
{
"x": 520.0,
"y": -53.0,
"type": "cubic"
},
{
"x": 572.0,
"y": -32.0,
"type": "cubic"
},
{
"x": 573.0,
"y": -25.0
},
{
"x": 573.0,
"y": 246.0
},
{
"x": 587.0,
"y": 249.0,
"type": "cubic"
},
{
"x": 597.0,
"y": 255.0,
"type": "cubic"
},
{
"x": 601.0,
"y": 261.0
},
{
"x": 507.0,
"y": 332.0
}
],
"isClosed": true
},
{
"points": [
{
"x": 329.0,
"y": 329.0
},
{
"x": 329.0,
"y": -68.0
},
{
"x": 348.0,
"y": -68.0,
"smooth": true
},
{
"x": 401.0,
"y": -68.0,
"type": "cubic"
},
{
"x": 433.0,
"y": -45.0,
"type": "cubic"
},
{
"x": 433.0,
"y": -38.0,
"smooth": true
},
{
"x": 433.0,
"y": 284.0
},
{
"x": 446.0,
"y": 284.0
}
],
"isClosed": true
},
{
"points": [
{
"x": 527.0,
"y": 475.0
},
{
"x": 485.0,
"y": 419.0
},
{
"x": 343.0,
"y": 419.0
},
{
"x": 351.0,
"y": 391.0
},
{
"x": 577.0,
"y": 391.0,
"smooth": true
},
{
"x": 591.0,
"y": 391.0,
"type": "cubic"
},
{
"x": 600.0,
"y": 396.0,
"type": "cubic"
},
{
"x": 602.0,
"y": 407.0
},
{
"x": 574.0,
"y": 436.0,
"type": "cubic"
},
{
"x": 527.0,
"y": 475.0,
"type": "cubic"
}
],
"isClosed": true
},
{
"points": [
{
"x": 518.0,
"y": 594.0
},
{
"x": 476.0,
"y": 538.0
},
{
"x": 334.0,
"y": 538.0
},
{
"x": 342.0,
"y": 510.0
},
{
"x": 568.0,
"y": 510.0,
"smooth": true
},
{
"x": 582.0,
"y": 510.0,
"type": "cubic"
},
{
"x": 591.0,
"y": 515.0,
"type": "cubic"
},
{
"x": 593.0,
"y": 526.0
},
{
"x": 565.0,
"y": 555.0,
"type": "cubic"
},
{
"x": 518.0,
"y": 594.0,
"type": "cubic"
}
],
"isClosed": true
},
{
"points": [
{
"x": 539.0,
"y": 726.0
},
{
"x": 493.0,
"y": 663.0
},
{
"x": 313.0,
"y": 663.0
},
{
"x": 321.0,
"y": 635.0
},
{
"x": 597.0,
"y": 635.0,
"smooth": true
},
{
"x": 610.0,
"y": 635.0,
"type": "cubic"
},
{
"x": 620.0,
"y": 640.0,
"type": "cubic"
},
{
"x": 623.0,
"y": 651.0
},
{
"x": 592.0,
"y": 682.0,
"type": "cubic"
},
{
"x": 539.0,
"y": 726.0,
"type": "cubic"
}
],
"isClosed": true
},
{
"points": [
{
"x": 536.0,
"y": 55.0
},
{
"x": 385.0,
"y": 55.0
},
{
"x": 385.0,
"y": 27.0
},
{
"x": 536.0,
"y": 27.0
}
],
"isClosed": true
},
{
"points": [
{
"x": 536.0,
"y": 284.0
},
{
"x": 385.0,
"y": 284.0
},
{
"x": 385.0,
"y": 256.0
},
{
"x": 536.0,
"y": 256.0
}
],
"isClosed": true
},
{
"points": [
{
"x": 245.0,
"y": 520.0
},
{
"x": 234.0,
"y": 515.0
},
{
"x": 254.0,
"y": 473.0,
"type": "cubic"
},
{
"x": 270.0,
"y": 409.0,
"type": "cubic"
},
{
"x": 264.0,
"y": 355.0
},
{
"x": 340.0,
"y": 275.0,
"type": "cubic"
},
{
"x": 450.0,
"y": 433.0,
"type": "cubic"
}
],
"isClosed": true
},
{
"points": [
{
"x": 288.0,
"y": 841.0
},
{
"x": 139.0,
"y": 856.0
},
{
"x": 139.0,
"y": -96.0
},
{
"x": 161.0,
"y": -96.0,
"smooth": true
},
{
"x": 203.0,
"y": -96.0,
"type": "cubic"
},
{
"x": 251.0,
"y": -69.0,
"type": "cubic"
},
{
"x": 251.0,
"y": -56.0,
"smooth": true
},
{
"x": 251.0,
"y": 813.0
},
{
"x": 278.0,
"y": 817.0,
"type": "cubic"
},
{
"x": 285.0,
"y": 827.0,
"type": "cubic"
}
],
"isClosed": true
},
{
"points": [
{
"x": 249.0,
"y": 584.0
},
{
"x": 249.0,
"y": 600.0
},
{
"x": 123.0,
"y": 600.0
},
{
"x": 108.0,
"y": 446.0,
"type": "cubic"
},
{
"x": 78.0,
"y": 276.0,
"type": "cubic"
},
{
"x": 20.0,
"y": 154.0
},
{
"x": 33.0,
"y": 143.0
},
{
"x": 146.0,
"y": 261.0,
"type": "cubic"
},
{
"x": 219.0,
"y": 409.0,
"type": "cubic"
}
],
"isClosed": true
},
{
"points": [
{
"x": 299.0,
"y": 684.0
},
{
"x": 256.0,
"y": 614.0
},
{
"x": 25.0,
"y": 614.0
},
{
"x": 33.0,
"y": 586.0
},
{
"x": 350.0,
"y": 586.0,
"smooth": true
},
{
"x": 364.0,
"y": 586.0,
"type": "cubic"
},
{
"x": 373.0,
"y": 591.0,
"type": "cubic"
},
{
"x": 376.0,
"y": 602.0
},
{
"x": 349.0,
"y": 634.0,
"type": "cubic"
},
{
"x": 299.0,
"y": 684.0,
"type": "cubic"
}
],
"isClosed": true
}
]
},
"xAdvance": 1000.0
}
}
}
}
