{
"name": "uni8413",
"sources": [
{
"name": "<default>",
"layerName": "<default>",
"location": {
"wght": 0
}
},
{
"name": "wght=1",
"layerName": "wght=1",
"location": {
"wght": 1.0
}
}
],
"layers": {
"<default>": {
"glyph": {
"path": {
"contours": [
{
"points": [
{
"x": 292,
"y": 285
},
{
"x": 292,
"y": 255
},
{
"x": 708,
"y": 255
},
{
"x": 708,
"y": 285
}
],
"isClosed": true
},
{
"points": [
{
"x": 292,
"y": 134
},
{
"x": 292,
"y": 105
},
{
"x": 708,
"y": 105
},
{
"x": 708,
"y": 134
}
],
"isClosed": true
},
{
"points": [
{
"x": 279,
"y": 432
},
{
"x": 279,
"y": -35
},
{
"x": 323,
"y": -35
},
{
"x": 323,
"y": 402
},
{
"x": 678,
"y": 402
},
{
"x": 678,
"y": -35
},
{
"x": 722,
"y": -35
},
{
"x": 722,
"y": 394
},
{
"x": 747,
"y": 397,
"type": "cubic"
},
{
"x": 761,
"y": 402,
"type": "cubic"
},
{
"x": 767,
"y": 412
},
{
"x": 695,
"y": 469
},
{
"x": 666,
"y": 432
},
{
"x": 335,
"y": 432
},
{
"x": 279,
"y": 458
}
],
"isClosed": true
},
{
"points": [
{
"x": 44,
"y": -22
},
{
"x": 53,
"y": -51
},
{
"x": 931,
"y": -51,
"smooth": true
},
{
"x": 945,
"y": -51,
"type": "cubic"
},
{
"x": 955,
"y": -46,
"type": "cubic"
},
{
"x": 957,
"y": -35
},
{
"x": 926,
"y": -7,
"type": "cubic"
},
{
"x": 878,
"y": 32,
"type": "cubic"
},
{
"x": 878,
"y": 32
},
{
"x": 834,
"y": -22
}
],
"isClosed": true
},
{
"points": [
{
"x": 46,
"y": 726
},
{
"x": 53,
"y": 696
},
{
"x": 317,
"y": 696
},
{
"x": 317,
"y": 600
},
{
"x": 324,
"y": 600,
"smooth": true
},
{
"x": 341,
"y": 600,
"type": "cubic"
},
{
"x": 362,
"y": 607,
"type": "cubic"
},
{
"x": 362,
"y": 615,
"smooth": true
},
{
"x": 362,
"y": 696
},
{
"x": 631,
"y": 696
},
{
"x": 631,
"y": 602
},
{
"x": 638,
"y": 602,
"smooth": true
},
{
"x": 662,
"y": 603,
"type": "cubic"
},
{
"x": 675,
"y": 613,
"type": "cubic"
},
{
"x": 675,
"y": 619,
"smooth": true
},
{
"x": 675,
"y": 696
},
{
"x": 925,
"y": 696,
"smooth": true
},
{
"x": 939,
"y": 696,
"type": "cubic"
},
{
"x": 949,
"y": 701,
"type": "cubic"
},
{
"x": 951,
"y": 712
},
{
"x": 922,
"y": 739,
"type": "cubic"
},
{
"x": 874,
"y": 778,
"type": "cubic"
},
{
"x": 874,
"y": 778
},
{
"x": 831,
"y": 726
},
{
"x": 675,
"y": 726
},
{
"x": 675,
"y": 801
},
{
"x": 699,
"y": 804,
"type": "cubic"
},
{
"x": 708,
"y": 814,
"type": "cubic"
},
{
"x": 710,
"y": 827
},
{
"x": 631,
"y": 836
},
{
"x": 631,
"y": 726
},
{
"x": 362,
"y": 726
},
{
"x": 362,
"y": 801
},
{
"x": 386,
"y": 804,
"type": "cubic"
},
{
"x": 395,
"y": 814,
"type": "cubic"
},
{
"x": 397,
"y": 827
},
{
"x": 317,
"y": 836
},
{
"x": 317,
"y": 726
}
],
"isClosed": true
},
{
"points": [
{
"x": 473,
"y": 664
},
{
"x": 473,
"y": 531
},
{
"x": 517,
"y": 531
},
{
"x": 517,
"y": 630
},
{
"x": 539,
"y": 633,
"type": "cubic"
},
{
"x": 548,
"y": 642,
"type": "cubic"
},
{
"x": 550,
"y": 655
}
],
"isClosed": true
},
{
"points": [
{
"x": 153,
"y": 607
},
{
"x": 153,
"y": 536,
"type": "cubic"
},
{
"x": 118,
"y": 465,
"type": "cubic"
},
{
"x": 81,
"y": 437,
"smooth": true
},
{
"x": 65,
"y": 425,
"type": "cubic"
},
{
"x": 56,
"y": 406,
"type": "cubic"
},
{
"x": 66,
"y": 391
},
{
"x": 78,
"y": 375,
"type": "cubic"
},
{
"x": 108,
"y": 384,
"type": "cubic"
},
{
"x": 128,
"y": 403,
"smooth": true
},
{
"x": 159,
"y": 432,
"type": "cubic"
},
{
"x": 193,
"y": 502,
"type": "cubic"
},
{
"x": 171,
"y": 607
}
],
"isClosed": true
},
{
"points": [
{
"x": 865,
"y": 552
},
{
"x": 850,
"y": 513,
"type": "cubic"
},
{
"x": 812,
"y": 442,
"type": "cubic"
},
{
"x": 788,
"y": 404
},
{
"x": 804,
"y": 396
},
{
"x": 838,
"y": 427,
"type": "cubic"
},
{
"x": 888,
"y": 480,
"type": "cubic"
},
{
"x": 913,
"y": 515
},
{
"x": 932,
"y": 516,
"type": "cubic"
},
{
"x": 944,
"y": 518,
"type": "cubic"
},
{
"x": 952,
"y": 525
},
{
"x": 889,
"y": 586
},
{
"x": 854,
"y": 552
}
],
"isClosed": true
},
{
"points": [
{
"x": 162,
"y": 552
},
{
"x": 162,
"y": 522
},
{
"x": 875,
"y": 522
},
{
"x": 875,
"y": 552
}
],
"isClosed": true
}
]
},
"xAdvance": 1000
}
},
"wght=1": {
"glyph": {
"path": {
"contours": [
{
"points": [
{
"x": 276.0,
"y": 275.0
},
{
"x": 276.0,
"y": 247.0
},
{
"x": 713.0,
"y": 247.0
},
{
"x": 713.0,
"y": 275.0
}
],
"isClosed": true
},
{
"points": [
{
"x": 276.0,
"y": 121.0
},
{
"x": 276.0,
"y": 93.0
},
{
"x": 713.0,
"y": 93.0
},
{
"x": 713.0,
"y": 121.0
}
],
"isClosed": true
},
{
"points": [
{
"x": 255.0,
"y": 426.0
},
{
"x": 255.0,
"y": -52.0
},
{
"x": 389.0,
"y": -52.0
},
{
"x": 389.0,
"y": 398.0
},
{
"x": 604.0,
"y": 398.0
},
{
"x": 604.0,
"y": -52.0
},
{
"x": 745.0,
"y": -52.0
},
{
"x": 745.0,
"y": 385.0
},
{
"x": 771.0,
"y": 389.0,
"type": "cubic"
},
{
"x": 783.0,
"y": 395.0,
"type": "cubic"
},
{
"x": 790.0,
"y": 406.0
},
{
"x": 652.0,
"y": 500.0
},
{
"x": 594.0,
"y": 426.0
},
{
"x": 398.0,
"y": 426.0
},
{
"x": 255.0,
"y": 480.0
}
],
"isClosed": true
},
{
"points": [
{
"x": 27.0,
"y": -36.0
},
{
"x": 35.0,
"y": -64.0
},
{
"x": 946.0,
"y": -64.0,
"smooth": true
},
{
"x": 961.0,
"y": -64.0,
"type": "cubic"
},
{
"x": 972.0,
"y": -59.0,
"type": "cubic"
},
{
"x": 975.0,
"y": -48.0
},
{
"x": 928.0,
"y": -6.0,
"type": "cubic"
},
{
"x": 851.0,
"y": 55.0,
"type": "cubic"
},
{
"x": 851.0,
"y": 55.0
},
{
"x": 782.0,
"y": -36.0
}
],
"isClosed": true
},
{
"points": [
{
"x": 27.0,
"y": 736.0
},
{
"x": 34.0,
"y": 708.0
},
{
"x": 260.0,
"y": 708.0
},
{
"x": 260.0,
"y": 611.0
},
{
"x": 283.0,
"y": 611.0,
"smooth": true
},
{
"x": 347.0,
"y": 611.0,
"type": "cubic"
},
{
"x": 401.0,
"y": 629.0,
"type": "cubic"
},
{
"x": 401.0,
"y": 640.0,
"smooth": true
},
{
"x": 401.0,
"y": 708.0
},
{
"x": 588.0,
"y": 708.0
},
{
"x": 588.0,
"y": 617.0
},
{
"x": 611.0,
"y": 617.0,
"smooth": true
},
{
"x": 678.0,
"y": 617.0,
"type": "cubic"
},
{
"x": 732.0,
"y": 634.0,
"type": "cubic"
},
{
"x": 732.0,
"y": 644.0,
"smooth": true
},
{
"x": 732.0,
"y": 708.0
},
{
"x": 944.0,
"y": 708.0,
"smooth": true
},
{
"x": 958.0,
"y": 708.0,
"type": "cubic"
},
{
"x": 969.0,
"y": 713.0,
"type": "cubic"
},
{
"x": 972.0,
"y": 724.0
},
{
"x": 929.0,
"y": 765.0,
"type": "cubic"
},
{
"x": 854.0,
"y": 824.0,
"type": "cubic"
},
{
"x": 854.0,
"y": 824.0
},
{
"x": 789.0,
"y": 736.0
},
{
"x": 732.0,
"y": 736.0
},
{
"x": 732.0,
"y": 815.0
},
{
"x": 758.0,
"y": 819.0,
"type": "cubic"
},
{
"x": 766.0,
"y": 828.0,
"type": "cubic"
},
{
"x": 767.0,
"y": 842.0
},
{
"x": 588.0,
"y": 856.0
},
{
"x": 588.0,
"y": 736.0
},
{
"x": 401.0,
"y": 736.0
},
{
"x": 401.0,
"y": 815.0
},
{
"x": 427.0,
"y": 819.0,
"type": "cubic"
},
{
"x": 434.0,
"y": 828.0,
"type": "cubic"
},
{
"x": 435.0,
"y": 841.0
},
{
"x": 260.0,
"y": 856.0
},
{
"x": 260.0,
"y": 736.0
}
],
"isClosed": true
},
{
"points": [
{
"x": 424.0,
"y": 669.0
},
{
"x": 424.0,
"y": 543.0
},
{
"x": 564.0,
"y": 543.0
},
{
"x": 564.0,
"y": 633.0
},
{
"x": 585.0,
"y": 636.0,
"type": "cubic"
},
{
"x": 590.0,
"y": 644.0,
"type": "cubic"
},
{
"x": 592.0,
"y": 656.0
}
],
"isClosed": true
},
{
"points": [
{
"x": 165.0,
"y": 620.0
},
{
"x": 167.0,
"y": 560.0,
"type": "cubic"
},
{
"x": 125.0,
"y": 508.0,
"type": "cubic"
},
{
"x": 86.0,
"y": 488.0,
"smooth": true
},
{
"x": 51.0,
"y": 472.0,
"type": "cubic"
},
{
"x": 27.0,
"y": 440.0,
"type": "cubic"
},
{
"x": 40.0,
"y": 399.0,
"smooth": true
},
{
"x": 55.0,
"y": 356.0,
"type": "cubic"
},
{
"x": 107.0,
"y": 343.0,
"type": "cubic"
},
{
"x": 145.0,
"y": 366.0,
"smooth": true
},
{
"x": 200.0,
"y": 398.0,
"type": "cubic"
},
{
"x": 234.0,
"y": 490.0,
"type": "cubic"
},
{
"x": 177.0,
"y": 620.0
}
],
"isClosed": true
},
{
"points": [
{
"x": 783.0,
"y": 552.0
},
{
"x": 781.0,
"y": 512.0,
"type": "cubic"
},
{
"x": 773.0,
"y": 444.0,
"type": "cubic"
},
{
"x": 765.0,
"y": 400.0
},
{
"x": 772.0,
"y": 394.0
},
{
"x": 821.0,
"y": 419.0,
"type": "cubic"
},
{
"x": 884.0,
"y": 462.0,
"type": "cubic"
},
{
"x": 921.0,
"y": 495.0
},
{
"x": 942.0,
"y": 497.0,
"type": "cubic"
},
{
"x": 952.0,
"y": 500.0,
"type": "cubic"
},
{
"x": 960.0,
"y": 509.0
},
{
"x": 841.0,
"y": 621.0
},
{
"x": 772.0,
"y": 552.0
}
],
"isClosed": true
},
{
"points": [
{
"x": 166.0,
"y": 552.0
},
{
"x": 166.0,
"y": 524.0
},
{
"x": 866.0,
"y": 524.0
},
{
"x": 866.0,
"y": 552.0
}
],
"isClosed": true
}
]
},
"xAdvance": 1000.0
}
}
}
}
