{
"name": "uni866C",
"sources": [
{
"name": "<default>",
"layerName": "<default>",
"location": {
"wght": 0
},
"customData": {
"fontra.development.status": 1
}
},
{
"name": "wght=1",
"layerName": "wght=1",
"location": {
"wght": 1.0
},
"customData": {
"fontra.development.status": 1
}
}
],
"layers": {
"<default>": {
"glyph": {
"components": [
{
"name": "VG_4E5A_00",
"transformation": {
"translateX": 393,
"translateY": -12
},
"location": {
"width": 333.148993288591,
"height": 870,
"tooth": 89.7986577181208,
"barb": 1,
"h-thick": 1.65548098434004,
"v-thick": 0.12826249067859607
}
},
{
"name": "VG_4E28_00",
"transformation": {
"translateX": -210,
"translateY": 130
},
"location": {
"length": 777.091820745848,
"barb": 1,
"thickness": 0,
"start_slope": 0,
"crop_corner": 0,
"flat_end": 0.585187506528779,
"barb_size": 0,
"barb_slope": 0
}
},
{
"name": "VG_53E3_00",
"transformation": {
"translateX": -213,
"translateY": 79
},
"location": {
"width": 443.773111877155,
"height": 467.467356105714,
"thickness_v": 0,
"thickness_h": 0,
"leg_left": -51.1542881019534,
"leg_right": -63.1881332915491,
"corner_node": -3.27796928862426,
"corner_length": 13.1432152930116
}
},
{
"name": "VG_rise_00",
"transformation": {
"translateX": 14,
"translateY": -244,
"rotation": -8,
"tCenterX": 82,
"tCenterY": 272
},
"location": {
"width": -38.1280685260629,
"start_slope": -6.922594797869
}
},
{
"name": "VG_4E36_00",
"transformation": {
"translateX": 82,
"translateY": -390,
"rotation": -22,
"tCenterX": 336,
"tCenterY": 601
},
"location": {
"length": 159.015982450642,
"thickness": 0
}
}
],
"xAdvance": 1000
}
},
"wght=1": {
"glyph": {
"components": [
{
"name": "VG_4E5A_00",
"transformation": {
"translateX": 405,
"translateY": -15
},
"location": {
"width": 320.778523489933,
"height": 880.402684563758,
"tooth": 56.8680089485459,
"barb": 1,
"h-thick": -14.3847874720358,
"v-thick": -2.54436987322893
}
},
{
"name": "VG_4E28_00",
"transformation": {
"translateX": -193,
"translateY": 190
},
"location": {
"length": 710.905672203071,
"barb": 1,
"thickness": -25.2752533166197,
"start_slope": 0,
"crop_corner": 0,
"flat_end": 0.585187506528779,
"barb_size": 0,
"barb_slope": 0
}
},
{
"name": "VG_53E3_00",
"transformation": {
"translateX": -203,
"translateY": 88
},
"location": {
"width": 432.541523033532,
"height": 455,
"thickness_v": -30.1598245064243,
"thickness_h": 0,
"leg_left": -76.5590723911,
"leg_right": -76.5590723911,
"corner_node": 5.27943173508827,
"corner_length": 0
}
},
{
"name": "VG_rise_00",
"transformation": {
"translateX": 3,
"translateY": -233,
"rotation": -3,
"tCenterX": 82,
"tCenterY": 272
},
"location": {
"width": -46.1506319857934,
"start_slope": -9.73049200877468
}
},
{
"name": "VG_4E36_00",
"transformation": {
"translateX": 100.40293279929597,
"translateY": -358.63798241727494,
"rotation": -26,
"tCenterX": 303,
"tCenterY": 601
},
"location": {
"length": 167.011804032174,
"thickness": -4.34764441658832
}
}
],
"xAdvance": 1000.0
}
}
}
}
