{
"name": "glyph00503",
"sources": [
{
"name": "<default>",
"layerName": "<default>",
"location": {
"wght": 0
}
},
{
"name": "wght=1",
"layerName": "wght=1",
"location": {
"wght": 1.0
}
}
],
"layers": {
"<default>": {
"glyph": {
"path": {
"contours": [
{
"points": [
{
"x": 202,
"y": 537
},
{
"x": 202,
"y": 508
},
{
"x": 812,
"y": 508
},
{
"x": 812,
"y": 537
}
],
"isClosed": true
},
{
"points": [
{
"x": 533,
"y": 523
},
{
"x": 510,
"y": 514
},
{
"x": 567,
"y": 363,
"type": "cubic"
},
{
"x": 681,
"y": 218,
"type": "cubic"
},
{
"x": 800,
"y": 150
},
{
"x": 805,
"y": 158,
"type": "cubic"
},
{
"x": 814,
"y": 168,
"type": "cubic"
},
{
"x": 821,
"y": 173
},
{
"x": 702,
"y": 233,
"type": "cubic"
},
{
"x": 589,
"y": 376,
"type": "cubic"
}
],
"isClosed": true
},
{
"points": [
{
"x": 483,
"y": 699
},
{
"x": 483,
"y": 82
},
{
"x": 513,
"y": 82
},
{
"x": 513,
"y": 699
}
],
"isClosed": true
},
{
"points": [
{
"x": 469,
"y": 530
},
{
"x": 413,
"y": 383,
"type": "cubic"
},
{
"x": 301,
"y": 236,
"type": "cubic"
},
{
"x": 189,
"y": 173
},
{
"x": 196,
"y": 167,
"type": "cubic"
},
{
"x": 205,
"y": 158,
"type": "cubic"
},
{
"x": 211,
"y": 150
},
{
"x": 323,
"y": 221,
"type": "cubic"
},
{
"x": 434,
"y": 369,
"type": "cubic"
},
{
"x": 492,
"y": 522
}
],
"isClosed": true
},
{
"points": [
{
"x": 95,
"y": 779
},
{
"x": 95,
"y": -72
},
{
"x": 125,
"y": -72
},
{
"x": 125,
"y": 750
},
{
"x": 877,
"y": 750
},
{
"x": 877,
"y": -72
},
{
"x": 907,
"y": -72
},
{
"x": 907,
"y": 779
}
],
"isClosed": true
},
{
"points": [
{
"x": 110,
"y": 8
},
{
"x": 110,
"y": -21
},
{
"x": 891,
"y": -21
},
{
"x": 891,
"y": 8
}
],
"isClosed": true
}
]
},
"xAdvance": 1000
}
},
"wght=1": {
"glyph": {
"path": {
"contours": [
{
"points": [
{
"x": 244.0,
"y": 560.0
},
{
"x": 244.0,
"y": 439.0
},
{
"x": 753.0,
"y": 439.0
},
{
"x": 753.0,
"y": 560.0
}
],
"isClosed": true
},
{
"points": [
{
"x": 577.0,
"y": 512.0
},
{
"x": 485.0,
"y": 485.0
},
{
"x": 526.0,
"y": 353.0,
"type": "cubic"
},
{
"x": 595.0,
"y": 222.0,
"type": "cubic"
},
{
"x": 682.0,
"y": 149.0
},
{
"x": 703.0,
"y": 183.0,
"type": "cubic"
},
{
"x": 746.0,
"y": 232.0,
"type": "cubic"
},
{
"x": 775.0,
"y": 256.0
},
{
"x": 690.0,
"y": 311.0,
"type": "cubic"
},
{
"x": 616.0,
"y": 412.0,
"type": "cubic"
}
],
"isClosed": true
},
{
"points": [
{
"x": 428.0,
"y": 664.0
},
{
"x": 428.0,
"y": 101.0
},
{
"x": 562.0,
"y": 101.0
},
{
"x": 562.0,
"y": 664.0
}
],
"isClosed": true
},
{
"points": [
{
"x": 405.0,
"y": 513.0
},
{
"x": 368.0,
"y": 406.0,
"type": "cubic"
},
{
"x": 296.0,
"y": 298.0,
"type": "cubic"
},
{
"x": 211.0,
"y": 240.0
},
{
"x": 239.0,
"y": 217.0,
"type": "cubic"
},
{
"x": 279.0,
"y": 171.0,
"type": "cubic"
},
{
"x": 299.0,
"y": 141.0
},
{
"x": 391.0,
"y": 216.0,
"type": "cubic"
},
{
"x": 464.0,
"y": 347.0,
"type": "cubic"
},
{
"x": 506.0,
"y": 483.0
}
],
"isClosed": true
},
{
"points": [
{
"x": 67.0,
"y": 814.0
},
{
"x": 67.0,
"y": -98.0
},
{
"x": 212.0,
"y": -98.0
},
{
"x": 212.0,
"y": 680.0
},
{
"x": 784.0,
"y": 680.0
},
{
"x": 784.0,
"y": -98.0
},
{
"x": 936.0,
"y": -98.0
},
{
"x": 936.0,
"y": 814.0
}
],
"isClosed": true
},
{
"points": [
{
"x": 152.0,
"y": 78.0
},
{
"x": 152.0,
"y": -56.0
},
{
"x": 841.0,
"y": -56.0
},
{
"x": 841.0,
"y": 78.0
}
],
"isClosed": true
}
]
},
"xAdvance": 1000.0
}
}
}
}
