{
"name": "glyph01431",
"sources": [
{
"name": "<default>",
"layerName": "<default>",
"location": {
"wght": 0
}
},
{
"name": "wght=1",
"layerName": "wght=1",
"location": {
"wght": 1.0
}
}
],
"layers": {
"<default>": {
"glyph": {
"path": {
"contours": [
{
"points": [
{
"x": 198,
"y": 22
},
{
"x": 198,
"y": -8
},
{
"x": 803,
"y": -8
},
{
"x": 803,
"y": 22
}
],
"isClosed": true
},
{
"points": [
{
"x": 198,
"y": 380
},
{
"x": 198,
"y": 351
},
{
"x": 803,
"y": 351
},
{
"x": 803,
"y": 380
}
],
"isClosed": true
},
{
"points": [
{
"x": 198,
"y": 203
},
{
"x": 198,
"y": 174
},
{
"x": 803,
"y": 174
},
{
"x": 803,
"y": 203
}
],
"isClosed": true
},
{
"points": [
{
"x": 184,
"y": 555
},
{
"x": 184,
"y": -67
},
{
"x": 214,
"y": -67
},
{
"x": 214,
"y": 525
},
{
"x": 786,
"y": 525
},
{
"x": 786,
"y": -67
},
{
"x": 816,
"y": -67
},
{
"x": 816,
"y": 555
}
],
"isClosed": true
},
{
"points": [
{
"x": 311,
"y": 830
},
{
"x": 311,
"y": 596
},
{
"x": 340,
"y": 596
},
{
"x": 340,
"y": 830
}
],
"isClosed": true
},
{
"points": [
{
"x": 655,
"y": 830
},
{
"x": 655,
"y": 596
},
{
"x": 684,
"y": 596
},
{
"x": 684,
"y": 830
}
],
"isClosed": true
},
{
"points": [
{
"x": 68,
"y": 743
},
{
"x": 68,
"y": 714
},
{
"x": 483,
"y": 714
},
{
"x": 483,
"y": 743
}
],
"isClosed": true
},
{
"points": [
{
"x": 520,
"y": 743
},
{
"x": 520,
"y": 714
},
{
"x": 935,
"y": 714
},
{
"x": 935,
"y": 743
}
],
"isClosed": true
}
]
},
"xAdvance": 1000
}
},
"wght=1": {
"glyph": {
"path": {
"contours": [
{
"points": [
{
"x": 240.0,
"y": 71.0
},
{
"x": 240.0,
"y": -58.0
},
{
"x": 772.0,
"y": -58.0
},
{
"x": 772.0,
"y": 71.0
}
],
"isClosed": true
},
{
"points": [
{
"x": 240.0,
"y": 402.0
},
{
"x": 240.0,
"y": 281.0
},
{
"x": 772.0,
"y": 281.0
},
{
"x": 772.0,
"y": 402.0
}
],
"isClosed": true
},
{
"points": [
{
"x": 240.0,
"y": 238.0
},
{
"x": 240.0,
"y": 117.0
},
{
"x": 772.0,
"y": 117.0
},
{
"x": 772.0,
"y": 238.0
}
],
"isClosed": true
},
{
"points": [
{
"x": 161.0,
"y": 575.0
},
{
"x": 161.0,
"y": -94.0
},
{
"x": 300.0,
"y": -94.0
},
{
"x": 300.0,
"y": 446.0
},
{
"x": 700.0,
"y": 446.0
},
{
"x": 700.0,
"y": -94.0
},
{
"x": 845.0,
"y": -94.0
},
{
"x": 845.0,
"y": 575.0
}
],
"isClosed": true
},
{
"points": [
{
"x": 250.0,
"y": 855.0
},
{
"x": 250.0,
"y": 598.0
},
{
"x": 394.0,
"y": 598.0
},
{
"x": 394.0,
"y": 855.0
}
],
"isClosed": true
},
{
"points": [
{
"x": 603.0,
"y": 855.0
},
{
"x": 603.0,
"y": 598.0
},
{
"x": 748.0,
"y": 598.0
},
{
"x": 748.0,
"y": 855.0
}
],
"isClosed": true
},
{
"points": [
{
"x": 53.0,
"y": 794.0
},
{
"x": 53.0,
"y": 667.0
},
{
"x": 490.0,
"y": 667.0
},
{
"x": 490.0,
"y": 794.0
}
],
"isClosed": true
},
{
"points": [
{
"x": 518.0,
"y": 794.0
},
{
"x": 518.0,
"y": 667.0
},
{
"x": 951.0,
"y": 667.0
},
{
"x": 951.0,
"y": 794.0
}
],
"isClosed": true
}
]
},
"xAdvance": 1000.0
}
}
}
}
