{
"name": "uni5586",
"sources": [
{
"name": "<default>",
"layerName": "<default>",
"location": {
"wght": 0
}
},
{
"name": "wght=1",
"layerName": "wght=1",
"location": {
"wght": 1.0
}
}
],
"layers": {
"<default>": {
"glyph": {
"path": {
"contours": [
{
"points": [
{
"x": 501,
"y": 672
},
{
"x": 501,
"y": 643
},
{
"x": 952,
"y": 643
},
{
"x": 952,
"y": 672
}
],
"isClosed": true
},
{
"points": [
{
"x": 526,
"y": 442
},
{
"x": 526,
"y": 413
},
{
"x": 928,
"y": 413
},
{
"x": 928,
"y": 442
}
],
"isClosed": true
},
{
"points": [
{
"x": 574,
"y": 2
},
{
"x": 574,
"y": -27
},
{
"x": 888,
"y": -27
},
{
"x": 888,
"y": 2
}
],
"isClosed": true
},
{
"points": [
{
"x": 709,
"y": 831
},
{
"x": 709,
"y": 429
},
{
"x": 738,
"y": 429
},
{
"x": 738,
"y": 831
}
],
"isClosed": true
},
{
"points": [
{
"x": 560,
"y": 294
},
{
"x": 560,
"y": -70
},
{
"x": 589,
"y": -70
},
{
"x": 589,
"y": 265
},
{
"x": 874,
"y": 265
},
{
"x": 874,
"y": -66
},
{
"x": 904,
"y": -66
},
{
"x": 904,
"y": 294
}
],
"isClosed": true
},
{
"points": [
{
"x": 49,
"y": 672
},
{
"x": 49,
"y": 643
},
{
"x": 474,
"y": 643
},
{
"x": 474,
"y": 672
}
],
"isClosed": true
},
{
"points": [
{
"x": 72,
"y": 442
},
{
"x": 72,
"y": 413
},
{
"x": 465,
"y": 413
},
{
"x": 465,
"y": 442
}
],
"isClosed": true
},
{
"points": [
{
"x": 251,
"y": 831
},
{
"x": 251,
"y": 429
},
{
"x": 280,
"y": 429
},
{
"x": 280,
"y": 831
}
],
"isClosed": true
},
{
"points": [
{
"x": 120,
"y": 4
},
{
"x": 120,
"y": -25
},
{
"x": 425,
"y": -25
},
{
"x": 425,
"y": 4
}
],
"isClosed": true
},
{
"points": [
{
"x": 105,
"y": 296
},
{
"x": 105,
"y": -68
},
{
"x": 134,
"y": -68
},
{
"x": 134,
"y": 267
},
{
"x": 413,
"y": 267
},
{
"x": 413,
"y": -65
},
{
"x": 442,
"y": -65
},
{
"x": 442,
"y": 296
}
],
"isClosed": true
}
]
},
"xAdvance": 1000
}
},
"wght=1": {
"glyph": {
"path": {
"contours": [
{
"points": [
{
"x": 493.0,
"y": 739.0
},
{
"x": 493.0,
"y": 605.0
},
{
"x": 975.0,
"y": 605.0
},
{
"x": 975.0,
"y": 739.0
}
],
"isClosed": true
},
{
"points": [
{
"x": 507.0,
"y": 515.0
},
{
"x": 507.0,
"y": 383.0
},
{
"x": 958.0,
"y": 383.0
},
{
"x": 958.0,
"y": 515.0
}
],
"isClosed": true
},
{
"points": [
{
"x": 608.0,
"y": 79.0
},
{
"x": 608.0,
"y": -51.0
},
{
"x": 856.0,
"y": -51.0
},
{
"x": 856.0,
"y": 79.0
}
],
"isClosed": true
},
{
"points": [
{
"x": 658.0,
"y": 854.0
},
{
"x": 658.0,
"y": 444.0
},
{
"x": 804.0,
"y": 444.0
},
{
"x": 804.0,
"y": 854.0
}
],
"isClosed": true
},
{
"points": [
{
"x": 528.0,
"y": 320.0
},
{
"x": 528.0,
"y": -94.0
},
{
"x": 663.0,
"y": -94.0
},
{
"x": 663.0,
"y": 190.0
},
{
"x": 800.0,
"y": 190.0
},
{
"x": 800.0,
"y": -90.0
},
{
"x": 942.0,
"y": -90.0
},
{
"x": 942.0,
"y": 320.0
}
],
"isClosed": true
},
{
"points": [
{
"x": 25.0,
"y": 739.0
},
{
"x": 25.0,
"y": 605.0
},
{
"x": 471.0,
"y": 605.0
},
{
"x": 471.0,
"y": 739.0
}
],
"isClosed": true
},
{
"points": [
{
"x": 46.0,
"y": 515.0
},
{
"x": 46.0,
"y": 383.0
},
{
"x": 461.0,
"y": 383.0
},
{
"x": 461.0,
"y": 515.0
}
],
"isClosed": true
},
{
"points": [
{
"x": 181.0,
"y": 854.0
},
{
"x": 181.0,
"y": 444.0
},
{
"x": 324.0,
"y": 444.0
},
{
"x": 324.0,
"y": 854.0
}
],
"isClosed": true
},
{
"points": [
{
"x": 138.0,
"y": 84.0
},
{
"x": 138.0,
"y": -43.0
},
{
"x": 386.0,
"y": -43.0
},
{
"x": 386.0,
"y": 84.0
}
],
"isClosed": true
},
{
"points": [
{
"x": 61.0,
"y": 320.0
},
{
"x": 61.0,
"y": -86.0
},
{
"x": 193.0,
"y": -86.0
},
{
"x": 193.0,
"y": 190.0
},
{
"x": 319.0,
"y": 190.0
},
{
"x": 319.0,
"y": -82.0
},
{
"x": 458.0,
"y": -82.0
},
{
"x": 458.0,
"y": 320.0
}
],
"isClosed": true
}
]
},
"xAdvance": 1000.0
}
}
}
}
